{
  "id": "fddc90cb-5838-46ba-8aa9-7f3cb5750f59",
  "prevId": "91df5164-7661-41d6-a2b9-d055a3b8328c",
  "version": "7",
  "dialect": "postgresql",
  "tables": {
    "public.homeworks": {
      "name": "homeworks",
      "schema": "",
      "columns": {
        "id": {
          "name": "id",
          "type": "uuid",
          "primaryKey": true,
          "notNull": true,
          "default": "gen_random_uuid()"
        },
        "student_id": {
          "name": "student_id",
          "type": "uuid",
          "primaryKey": false,
          "notNull": true
        },
        "subject": {
          "name": "subject",
          "type": "text",
          "primaryKey": false,
          "notNull": true
        },
        "description": {
          "name": "description",
          "type": "text",
          "primaryKey": false,
          "notNull": true
        },
        "status": {
          "name": "status",
          "type": "homework_status",
          "typeSchema": "public",
          "primaryKey": false,
          "notNull": true,
          "default": "'Pending'"
        },
        "created_at": {
          "name": "created_at",
          "type": "timestamp",
          "primaryKey": false,
          "notNull": false,
          "default": "now()"
        },
        "updated_at": {
          "name": "updated_at",
          "type": "timestamp",
          "primaryKey": false,
          "notNull": false,
          "default": "now()"
        }
      },
      "indexes": {},
      "foreignKeys": {
        "homeworks_student_id_students_id_fk": {
          "name": "homeworks_student_id_students_id_fk",
          "tableFrom": "homeworks",
          "tableTo": "students",
          "columnsFrom": [
            "student_id"
          ],
          "columnsTo": [
            "id"
          ],
          "onDelete": "no action",
          "onUpdate": "no action"
        }
      },
      "compositePrimaryKeys": {},
      "uniqueConstraints": {},
      "policies": {},
      "checkConstraints": {},
      "isRLSEnabled": false
    },
    "public.students": {
      "name": "students",
      "schema": "",
      "columns": {
        "id": {
          "name": "id",
          "type": "uuid",
          "primaryKey": true,
          "notNull": true,
          "default": "gen_random_uuid()"
        },
        "name": {
          "name": "name",
          "type": "text",
          "primaryKey": false,
          "notNull": true
        },
        "email": {
          "name": "email",
          "type": "text",
          "primaryKey": false,
          "notNull": true
        },
        "phone": {
          "name": "phone",
          "type": "text",
          "primaryKey": false,
          "notNull": true
        },
        "created_at": {
          "name": "created_at",
          "type": "timestamp",
          "primaryKey": false,
          "notNull": false,
          "default": "now()"
        }
      },
      "indexes": {},
      "foreignKeys": {},
      "compositePrimaryKeys": {},
      "uniqueConstraints": {
        "students_email_unique": {
          "name": "students_email_unique",
          "nullsNotDistinct": false,
          "columns": [
            "email"
          ]
        },
        "students_phone_unique": {
          "name": "students_phone_unique",
          "nullsNotDistinct": false,
          "columns": [
            "phone"
          ]
        }
      },
      "policies": {},
      "checkConstraints": {},
      "isRLSEnabled": false
    }
  },
  "enums": {
    "public.homework_status": {
      "name": "homework_status",
      "schema": "public",
      "values": [
        "Pending",
        "Completed",
        "Missed"
      ]
    }
  },
  "schemas": {},
  "sequences": {},
  "roles": {},
  "policies": {},
  "views": {},
  "_meta": {
    "columns": {},
    "schemas": {},
    "tables": {}
  }
}